kn_fancy_pack/__init__.py
kn_fancy_pack/cli.py
kn_fancy_pack/game.py
kn_fancy_pack-0.1.2.dist-info/METADATA
kn_fancy_pack-0.1.2.dist-info/WHEEL
kn_fancy_pack-0.1.2.dist-info/entry_points.txt
kn_fancy_pack-0.1.2.dist-info/top_level.txt
kn_fancy_pack-0.1.2.dist-info/RECORD
